odoo/addons/sale_backorder/README.rst
odoo/addons/sale_backorder/__init__.py
odoo/addons/sale_backorder/__manifest__.py
odoo/addons/sale_backorder/i18n/de.po
odoo/addons/sale_backorder/i18n/it.po
odoo/addons/sale_backorder/i18n/sale_backorder.pot
odoo/addons/sale_backorder/i18n/sl.po
odoo/addons/sale_backorder/models/__init__.py
odoo/addons/sale_backorder/models/sale.py
odoo/addons/sale_backorder/readme/CONTRIBUTORS.rst
odoo/addons/sale_backorder/readme/CREDITS.rst
odoo/addons/sale_backorder/readme/DESCRIPTION.rst
odoo/addons/sale_backorder/readme/USAGE.rst
odoo/addons/sale_backorder/report/so_backorder_report.xml
odoo/addons/sale_backorder/static/description/icon.png
odoo/addons/sale_backorder/static/description/index.html
odoo/addons/sale_backorder/views/sale_view.xml
odoo/addons/sale_backorder/views/so_backorder_view.xml
odoo/addons/sale_backorder/wizard/__init__.py
odoo/addons/sale_backorder/wizard/so_backorder_wizard.py
odoo/addons/sale_backorder/wizard/so_backorder_wizard_view.xml
odoo12_addon_sale_backorder-12.0.1.0.0.99.dev23.dist-info/METADATA
odoo12_addon_sale_backorder-12.0.1.0.0.99.dev23.dist-info/WHEEL
odoo12_addon_sale_backorder-12.0.1.0.0.99.dev23.dist-info/top_level.txt
odoo12_addon_sale_backorder-12.0.1.0.0.99.dev23.dist-info/RECORD
