Metadata-Version: 2.1
Name: odoo12-addon-sale_backorder
Version: 12.0.1.0.0.99.dev23
Summary: Report of Un-Invoice Goods Delivered and Backorders
Home-page: https://github.com/OCA/sale-reporting
Author: Open Source Integrators, Odoo Community Association (OCA)
Author-email: support@odoo-community.org
License: LGPL-3
Classifier: Programming Language :: Python
Classifier: Framework :: Odoo
Classifier: Framework :: Odoo :: 12.0
Classifier: License :: OSI Approved :: GNU Lesser General Public License v3 (LGPLv3)
Classifier: Development Status :: 4 - Beta
Requires-Python: >=3.5
Requires-Dist: odoo<12.1dev,>=12.0a
